kernelutility/__init__.py
kernelutility/constants.py
kernelutility/kernelset.py
kernelutility/meta.py
kernelutility-0.1.1.dist-info/METADATA
kernelutility-0.1.1.dist-info/WHEEL
kernelutility-0.1.1.dist-info/top_level.txt
kernelutility-0.1.1.dist-info/RECORD
