Metadata-Version: 2.1
Name: kernelutility
Version: 0.1.1
Summary: A Python package for managing Python kernels
Home-page: https://github.com/jpvantassel/kernelutility
Author: Joseph P. Vantassel
Author-email: jvantassel@tacc.utexas.edu
License: UNKNOWN
Keywords: jupyter kernel conda
Platform: UNKNOWN
Classifier: Development Status :: 4 - Beta
Classifier: Framework :: Jupyter
Classifier: Framework :: Jupyter :: JupyterLab
Classifier: License :: OSI Approved :: GNU General Public License v3 or later (GPLv3+)
Classifier: Programming Language :: Python :: 3.7
Classifier: Programming Language :: Python :: 3.8
Classifier: Programming Language :: Python :: 3.9
Classifier: Programming Language :: Python :: 3.10
Requires-Python: >3.7
